notions/__init__.py
notions/cli/__init__.py
notions/cli/api.py
notions/cli/config.py
notions/cli/database.py
notions/cli/main.py
notions/cli/page.py
notions/cli/run.py
notions/cli/search.py
notions/cli/yaml.py
notions/client.py
notions/flatten.py
notions/models/__init__.py
notions/models/color.py
notions/models/database.py
notions/models/number.py
notions/models/page.py
notions/models/parent.py
notions/models/request.py
notions/models/response.py
notions/models/rich_text.py
notions/models/update.py
notions/models/user.py
notions-0.3.0.dist-info/entry_points.txt
notions-0.3.0.dist-info/LICENSE.md
notions-0.3.0.dist-info/WHEEL
notions-0.3.0.dist-info/METADATA
notions-0.3.0.dist-info/RECORD
