Metadata-Version: 2.1
Name: notions
Version: 0.3.0
Summary: Client library for Notion API
Home-page: https://github.com/micktwomey/notions
License: MIT
Author: Michael Twomey
Author-email: mick@twomeylee.name
Requires-Python: >=3.8,<4.0
Classifier: License :: OSI Approved :: MIT License
Classifier: Programming Language :: Python :: 3
Classifier: Programming Language :: Python :: 3.8
Classifier: Programming Language :: Python :: 3.9
Requires-Dist: PyYAML (>=5.4.1,<6.0.0)
Requires-Dist: coloredlogs (>=15.0.1,<16.0.0)
Requires-Dist: furl (>=2.1.2,<3.0.0)
Requires-Dist: httpx (>=0.18.2,<0.19.0)
Requires-Dist: pydantic (>=1.8.2,<2.0.0)
Requires-Dist: typer (>=0.3.2,<0.4.0)
Requires-Dist: types-PyYAML (>=5.4.3,<6.0.0)
Project-URL: Repository, https://github.com/micktwomey/notions
